fsimport.py
fsimport-0.0.3.dist-info/LICENSE
fsimport-0.0.3.dist-info/METADATA
fsimport-0.0.3.dist-info/WHEEL
fsimport-0.0.3.dist-info/top_level.txt
fsimport-0.0.3.dist-info/RECORD
