Metadata-Version: 2.1
Name: fsimport
Version: 0.0.3
Summary: Import source file from the file system for Python
Home-page: https://github.com/pavelkukov/fsimport
Author: Pavel Kukov
Author-email: pavelkukov@gmail.com
License: UNKNOWN
Platform: UNKNOWN
Classifier: Programming Language :: Python :: 3
Classifier: License :: OSI Approved :: MIT License
Classifier: Operating System :: OS Independent
Requires-Python: >=3.6
